[
  {
    "spot": 4996.26,
    "metal": "Gold",
    "source": "hourly",
    "provider": "MetalPriceAPI",
    "timestamp": "2026-02-18 12:00:00"
  },
  {
    "spot": 77.6,
    "metal": "Silver",
    "source": "hourly",
    "provider": "MetalPriceAPI",
    "timestamp": "2026-02-18 12:00:00"
  },
  {
    "spot": 2093.85,
    "metal": "Platinum",
    "source": "hourly",
    "provider": "MetalPriceAPI",
    "timestamp": "2026-02-18 12:00:00"
  },
  {
    "spot": 1741.65,
    "metal": "Palladium",
    "source": "hourly",
    "provider": "MetalPriceAPI",
    "timestamp": "2026-02-18 12:00:00"
  }
]