[
  {
    "spot": 5107.03,
    "metal": "Gold",
    "source": "hourly",
    "provider": "StakTrakr",
    "timestamp": "2026-02-22 22:00:00"
  },
  {
    "spot": 84.75,
    "metal": "Silver",
    "source": "hourly",
    "provider": "StakTrakr",
    "timestamp": "2026-02-22 22:00:00"
  },
  {
    "spot": 2161.6,
    "metal": "Platinum",
    "source": "hourly",
    "provider": "StakTrakr",
    "timestamp": "2026-02-22 22:00:00"
  },
  {
    "spot": 1769.09,
    "metal": "Palladium",
    "source": "hourly",
    "provider": "StakTrakr",
    "timestamp": "2026-02-22 22:00:00"
  }
]