{
  "slug": "goldback-utah-g1",
  "window_start": "2026-03-06T12:00:00Z",
  "median_price": 10.51,
  "lowest_price": 9.94,
  "vendors": {
    "apmex": {
      "price": 10.51,
      "confidence": 80,
      "source": "firecrawl",
      "inStock": true
    },
    "sdbullion": {
      "price": 9.94,
      "confidence": 50,
      "source": "firecrawl",
      "inStock": true
    },
    "herobullion": {
      "price": 9.83,
      "confidence": null,
      "source": "turso_last_known",
      "inStock": true,
      "stale": true,
      "stale_since": "2026-03-06T07:00:03.373Z"
    }
  },
  "availability_by_site": {
    "apmex": true,
    "sdbullion": true,
    "bullionexchanges": true,
    "herobullion": true,
    "jmbullion": true
  },
  "last_known_price_by_site": {},
  "last_available_date_by_site": {},
  "windows_24h": [
    {
      "window": "2026-02-26T02:00:00Z",
      "median": 10.43,
      "low": 10.43,
      "vendors": {
        "goldback": 10.43
      }
    },
    {
      "window": "2026-02-26T18:30:00Z",
      "median": 10.36,
      "low": 10.36,
      "vendors": {
        "goldback": 10.36
      }
    },
    {
      "window": "2026-03-06T01:30:00Z",
      "median": 10.54,
      "low": 10.54,
      "vendors": {
        "apmex": 10.54
      }
    },
    {
      "window": "2026-03-06T02:00:00Z",
      "median": 10.61,
      "low": 10.61,
      "vendors": {
        "apmex": 10.61
      }
    },
    {
      "window": "2026-03-06T07:00:00Z",
      "median": 9.83,
      "low": 9.83,
      "vendors": {
        "herobullion": 9.83
      }
    },
    {
      "window": "2026-03-06T10:00:00Z",
      "median": 10.52,
      "low": 10.52,
      "vendors": {
        "apmex": 10.52
      }
    },
    {
      "window": "2026-03-06T10:30:00Z",
      "median": 9.95,
      "low": 9.95,
      "vendors": {
        "sdbullion": 9.95
      }
    },
    {
      "window": "2026-03-06T12:00:00Z",
      "median": 10.51,
      "low": 9.94,
      "vendors": {
        "sdbullion": 9.94,
        "apmex": 10.51
      }
    }
  ]
}
