[
  {
    "date": "2026-02-21",
    "avg_median": 5425.57,
    "avg_low": 5120.96,
    "sample_count": 44,
    "vendors": {
      "apmex": {
        "avg": null,
        "inStock": true
      },
      "bullionexchanges": {
        "avg": null,
        "inStock": true
      },
      "herobullion": {
        "avg": null,
        "inStock": true
      },
      "jmbullion": {
        "avg": 5120.96,
        "inStock": true
      },
      "monumentmetals": {
        "avg": null,
        "inStock": true
      },
      "sdbullion": {
        "avg": 5425.57,
        "inStock": true
      }
    }
  }
]
