[
  {
    "spot": 5172.05,
    "metal": "Gold",
    "source": "hourly",
    "provider": "StakTrakr",
    "timestamp": "2026-03-10 06:00:00"
  },
  {
    "spot": 1683.43,
    "metal": "Palladium",
    "source": "hourly",
    "provider": "StakTrakr",
    "timestamp": "2026-03-10 06:00:00"
  },
  {
    "spot": 2194.2,
    "metal": "Platinum",
    "source": "hourly",
    "provider": "StakTrakr",
    "timestamp": "2026-03-10 06:00:00"
  },
  {
    "spot": 88.95,
    "metal": "Silver",
    "source": "hourly",
    "provider": "StakTrakr",
    "timestamp": "2026-03-10 06:00:00"
  }
]
