[
  {
    "spot": 5193.4,
    "metal": "Gold",
    "source": "hourly",
    "provider": "StakTrakr",
    "timestamp": "2026-03-10 09:00:00"
  },
  {
    "spot": 1700.09,
    "metal": "Palladium",
    "source": "hourly",
    "provider": "StakTrakr",
    "timestamp": "2026-03-10 09:00:00"
  },
  {
    "spot": 2230.19,
    "metal": "Platinum",
    "source": "hourly",
    "provider": "StakTrakr",
    "timestamp": "2026-03-10 09:00:00"
  },
  {
    "spot": 89.36,
    "metal": "Silver",
    "source": "hourly",
    "provider": "StakTrakr",
    "timestamp": "2026-03-10 09:00:00"
  }
]
