[
  {
    "date": "2026-02-21",
    "avg_median": 5405.09,
    "avg_low": 5111,
    "sample_count": 161,
    "vendors": {
      "apmex": {
        "avg": 5437.59,
        "inStock": true
      },
      "bullionexchanges": {
        "avg": 5326,
        "inStock": true
      },
      "herobullion": {
        "avg": 5361.99,
        "inStock": true
      },
      "jmbullion": {
        "avg": 5485.45,
        "inStock": true
      },
      "monumentmetals": {
        "avg": 5360.83,
        "inStock": true
      },
      "sdbullion": {
        "avg": 5405.09,
        "inStock": true
      }
    }
  },
  {
    "date": "2026-02-22",
    "avg_median": 5362.59,
    "avg_low": 5111,
    "sample_count": 326,
    "vendors": {
      "apmex": {
        "avg": 5438.32,
        "inStock": true
      },
      "bullionexchanges": {
        "avg": 5326.61,
        "inStock": true
      },
      "herobullion": {
        "avg": 5362.59,
        "inStock": true
      },
      "jmbullion": {
        "avg": null,
        "inStock": true
      },
      "monumentmetals": {
        "avg": 5358.41,
        "inStock": true
      },
      "sdbullion": {
        "avg": 5405.71,
        "inStock": true
      }
    }
  },
  {
    "date": "2026-02-23",
    "avg_median": 5423,
    "avg_low": 5186.1,
    "sample_count": 340,
    "vendors": {
      "apmex": {
        "avg": 5498.06,
        "inStock": true
      },
      "bullionexchanges": {
        "avg": 5380.37,
        "inStock": true
      },
      "herobullion": {
        "avg": 5423,
        "inStock": true
      },
      "jmbullion": {
        "avg": null,
        "inStock": true
      },
      "monumentmetals": {
        "avg": 5413.97,
        "inStock": true
      },
      "sdbullion": {
        "avg": 5468.89,
        "inStock": true
      }
    }
  },
  {
    "date": "2026-02-24",
    "avg_median": 5464.27,
    "avg_low": 5129.4,
    "sample_count": 355,
    "vendors": {
      "apmex": {
        "avg": 5489.16,
        "inStock": true
      },
      "bullionexchanges": {
        "avg": 5382.25,
        "inStock": true
      },
      "herobullion": {
        "avg": 5412.49,
        "inStock": true
      },
      "jmbullion": {
        "avg": 5542.17,
        "inStock": true
      },
      "monumentmetals": {
        "avg": 5326.05,
        "inStock": true
      },
      "sdbullion": {
        "avg": 5464.27,
        "inStock": true
      }
    }
  },
  {
    "date": "2026-02-25",
    "avg_median": 5483.37,
    "avg_low": 5144.8,
    "sample_count": 477,
    "vendors": {
      "apmex": {
        "avg": 5508.74,
        "inStock": true
      },
      "bullionexchanges": {
        "avg": 5399.12,
        "inStock": true
      },
      "herobullion": {
        "avg": 5431.16,
        "inStock": true
      },
      "jmbullion": {
        "avg": 5504.09,
        "inStock": true
      },
      "monumentmetals": {
        "avg": 5303.45,
        "inStock": true
      },
      "sdbullion": {
        "avg": 5483.37,
        "inStock": true
      }
    }
  },
  {
    "date": "2026-02-26",
    "avg_median": 5485.59,
    "avg_low": 5166.1,
    "sample_count": 520,
    "vendors": {
      "apmex": {
        "avg": 5510.5,
        "inStock": true
      },
      "bullionexchanges": {
        "avg": 5368.41,
        "inStock": true
      },
      "herobullion": {
        "avg": 5428.82,
        "inStock": true
      },
      "jmbullion": {
        "avg": 5567.51,
        "inStock": true
      },
      "monumentmetals": {
        "avg": 5248.02,
        "inStock": true
      },
      "sdbullion": {
        "avg": 5485.59,
        "inStock": true
      }
    }
  },
  {
    "date": "2026-02-27",
    "avg_median": 5486.49,
    "avg_low": 5252.89,
    "sample_count": 285,
    "vendors": {
      "apmex": {
        "avg": 5517.47,
        "inStock": true
      },
      "bullionexchanges": {
        "avg": 5370.04,
        "inStock": true
      },
      "herobullion": {
        "avg": 5428.7,
        "inStock": true
      },
      "jmbullion": {
        "avg": 5568.27,
        "inStock": true
      },
      "monumentmetals": {
        "avg": 5265.77,
        "inStock": true
      },
      "sdbullion": {
        "avg": 5486.49,
        "inStock": true
      }
    }
  }
]
