[
  {
    "spot": 5309.51,
    "metal": "Gold",
    "source": "hourly",
    "provider": "StakTrakr",
    "timestamp": "2026-03-03 09:00:00"
  },
  {
    "spot": 5294.37,
    "metal": "Gold",
    "source": "hourly",
    "provider": "StakTrakr",
    "timestamp": "2026-03-03 09:15:00"
  },
  {
    "spot": 5296.52,
    "metal": "Gold",
    "source": "hourly",
    "provider": "StakTrakr",
    "timestamp": "2026-03-03 09:30:00"
  },
  {
    "spot": 1705.01,
    "metal": "Palladium",
    "source": "hourly",
    "provider": "StakTrakr",
    "timestamp": "2026-03-03 09:00:00"
  },
  {
    "spot": 1706.32,
    "metal": "Palladium",
    "source": "hourly",
    "provider": "StakTrakr",
    "timestamp": "2026-03-03 09:15:00"
  },
  {
    "spot": 1706.46,
    "metal": "Palladium",
    "source": "hourly",
    "provider": "StakTrakr",
    "timestamp": "2026-03-03 09:30:00"
  },
  {
    "spot": 2166.7,
    "metal": "Platinum",
    "source": "hourly",
    "provider": "StakTrakr",
    "timestamp": "2026-03-03 09:00:00"
  },
  {
    "spot": 2158.12,
    "metal": "Platinum",
    "source": "hourly",
    "provider": "StakTrakr",
    "timestamp": "2026-03-03 09:15:00"
  },
  {
    "spot": 2169.53,
    "metal": "Platinum",
    "source": "hourly",
    "provider": "StakTrakr",
    "timestamp": "2026-03-03 09:30:00"
  },
  {
    "spot": 85.77,
    "metal": "Silver",
    "source": "hourly",
    "provider": "StakTrakr",
    "timestamp": "2026-03-03 09:00:00"
  },
  {
    "spot": 85,
    "metal": "Silver",
    "source": "hourly",
    "provider": "StakTrakr",
    "timestamp": "2026-03-03 09:15:00"
  },
  {
    "spot": 85.23,
    "metal": "Silver",
    "source": "hourly",
    "provider": "StakTrakr",
    "timestamp": "2026-03-03 09:30:00"
  }
]
