[
  {
    "spot": 5194.74,
    "metal": "Gold",
    "source": "seed",
    "provider": "StakTrakr",
    "timestamp": "2026-02-26 06:05:00"
  },
  {
    "spot": 89.39,
    "metal": "Silver",
    "source": "seed",
    "provider": "StakTrakr",
    "timestamp": "2026-02-26 06:05:00"
  },
  {
    "spot": 2299.12,
    "metal": "Platinum",
    "source": "seed",
    "provider": "StakTrakr",
    "timestamp": "2026-02-26 06:05:00"
  },
  {
    "spot": 1786.77,
    "metal": "Palladium",
    "source": "seed",
    "provider": "StakTrakr",
    "timestamp": "2026-02-26 06:05:00"
  }
]