{
  "slug": "goldback-wyoming-g50",
  "window_start": "2026-02-26T05:00:00Z",
  "median_price": 516.02,
  "lowest_price": 516.02,
  "vendors": {
    "apmex": {
      "price": 516.02,
      "confidence": 80,
      "source": "firecrawl",
      "inStock": true
    }
  },
  "availability_by_site": {
    "apmex": true
  },
  "last_known_price_by_site": {},
  "last_available_date_by_site": {},
  "windows_24h": [
    {
      "window": "2026-02-26T02:00:00Z",
      "median": 260.75,
      "low": 260.75,
      "vendors": {
        "goldback": 260.75
      }
    },
    {
      "window": "2026-02-26T04:30:00Z",
      "median": 516.05,
      "low": 516.05,
      "vendors": {
        "apmex": 516.05
      }
    },
    {
      "window": "2026-02-26T05:00:00Z",
      "median": 516.02,
      "low": 516.02,
      "vendors": {
        "apmex": 516.02
      }
    }
  ]
}
