[
  {
    "spot": 5159.69,
    "metal": "Gold",
    "source": "hourly",
    "provider": "StakTrakr",
    "timestamp": "2026-03-05 00:00:00"
  },
  {
    "spot": 5164.74,
    "metal": "Gold",
    "source": "hourly",
    "provider": "StakTrakr",
    "timestamp": "2026-03-05 00:15:00"
  },
  {
    "spot": 5175.94,
    "metal": "Gold",
    "source": "hourly",
    "provider": "StakTrakr",
    "timestamp": "2026-03-05 00:30:00"
  },
  {
    "spot": 5171.9,
    "metal": "Gold",
    "source": "hourly",
    "provider": "StakTrakr",
    "timestamp": "2026-03-05 00:45:00"
  },
  {
    "spot": 1673.46,
    "metal": "Palladium",
    "source": "hourly",
    "provider": "StakTrakr",
    "timestamp": "2026-03-05 00:00:00"
  },
  {
    "spot": 1672.52,
    "metal": "Palladium",
    "source": "hourly",
    "provider": "StakTrakr",
    "timestamp": "2026-03-05 00:15:00"
  },
  {
    "spot": 1674.91,
    "metal": "Palladium",
    "source": "hourly",
    "provider": "StakTrakr",
    "timestamp": "2026-03-05 00:30:00"
  },
  {
    "spot": 1673.3,
    "metal": "Palladium",
    "source": "hourly",
    "provider": "StakTrakr",
    "timestamp": "2026-03-05 00:45:00"
  },
  {
    "spot": 2173,
    "metal": "Platinum",
    "source": "hourly",
    "provider": "StakTrakr",
    "timestamp": "2026-03-05 00:00:00"
  },
  {
    "spot": 2179.47,
    "metal": "Platinum",
    "source": "hourly",
    "provider": "StakTrakr",
    "timestamp": "2026-03-05 00:15:00"
  },
  {
    "spot": 2190.67,
    "metal": "Platinum",
    "source": "hourly",
    "provider": "StakTrakr",
    "timestamp": "2026-03-05 00:30:00"
  },
  {
    "spot": 2202.92,
    "metal": "Platinum",
    "source": "hourly",
    "provider": "StakTrakr",
    "timestamp": "2026-03-05 00:45:00"
  },
  {
    "spot": 83.91,
    "metal": "Silver",
    "source": "hourly",
    "provider": "StakTrakr",
    "timestamp": "2026-03-05 00:00:00"
  },
  {
    "spot": 84.11,
    "metal": "Silver",
    "source": "hourly",
    "provider": "StakTrakr",
    "timestamp": "2026-03-05 00:15:00"
  },
  {
    "spot": 84.26,
    "metal": "Silver",
    "source": "hourly",
    "provider": "StakTrakr",
    "timestamp": "2026-03-05 00:30:00"
  },
  {
    "spot": 84.15,
    "metal": "Silver",
    "source": "hourly",
    "provider": "StakTrakr",
    "timestamp": "2026-03-05 00:45:00"
  }
]
