[
  {
    "spot": 5064.16,
    "metal": "Gold",
    "source": "hourly",
    "provider": "StakTrakr",
    "timestamp": "2026-03-05 18:00:00"
  },
  {
    "spot": 1636.72,
    "metal": "Palladium",
    "source": "hourly",
    "provider": "StakTrakr",
    "timestamp": "2026-03-05 18:00:00"
  },
  {
    "spot": 2125.11,
    "metal": "Platinum",
    "source": "hourly",
    "provider": "StakTrakr",
    "timestamp": "2026-03-05 18:00:00"
  },
  {
    "spot": 81.59,
    "metal": "Silver",
    "source": "hourly",
    "provider": "StakTrakr",
    "timestamp": "2026-03-05 18:00:00"
  }
]
