[{"spot": 306.25, "metal": "Gold", "source": "seed", "provider": "LBMA", "timestamp": "1985-01-02 12:00:00"}, {"spot": 6.25, "metal": "Silver", "source": "seed", "provider": "LBMA", "timestamp": "1985-01-02 12:00:00"}, {"spot": 299.5, "metal": "Gold", "source": "seed", "provider": "LBMA", "timestamp": "1985-01-03 12:00:00"}, {"spot": 6.017, "metal": "Silver", "source": "seed", "provider": "LBMA", "timestamp": "1985-01-03 12:00:00"}, {"spot": 303.45, "metal": "Gold", "source": "seed", "provider": "LBMA", "timestamp": "1985-01-04 12:00:00"}, {"spot": 6.087, "metal": "Silver", "source": "seed", "provider": "LBMA", "timestamp": "1985-01-04 12:00:00"}, {"spot": 296.75, "metal": "Gold", "source": "seed", "provider": "LBMA", "timestamp": "1985-01-07 12:00:00"}, {"spot": 5.83, "metal": "Silver", "source": "seed", "provider": "LBMA", "timestamp": "1985-01-07 12:00:00"}, {"spot": 304.4, "metal": "Gold", "source": "seed", "provider": "LBMA", "timestamp": "1985-01-08 12:00:00"}, {"spot": 6.075, "metal": "Silver", "source": "seed", "provider": "LBMA", "timestamp": "1985-01-08 12:00:00"}, {"spot": 298.35, "metal": "Gold", "source": "seed", "provider": "LBMA", "timestamp": "1985-01-09 12:00:00"}, {"spot": 5.878, "metal": "Silver", "source": "seed", "provider": "LBMA", "timestamp": "1985-01-09 12:00:00"}, {"spot": 304.0, "metal": "Gold", "source": "seed", "provider": "LBMA", "timestamp": "1985-01-10 12:00:00"}, {"spot": 6.09, "metal": "Silver", "source": "seed", "provider": "LBMA", "timestamp": "1985-01-10 12:00:00"}, {"spot": 304.0, "metal": "Gold", "source": "seed", "provider": "LBMA", "timestamp": "1985-01-11 12:00:00"}, {"spot": 6.11, "metal": "Silver", "source": "seed", "provider": "LBMA", "timestamp": "1985-01-11 12:00:00"}, {"spot": 301.25, "metal": "Gold", "source": "seed", "provider": "LBMA", "timestamp": "1985-01-14 12:00:00"}, {"spot": 6.004, "metal": "Silver", "source": "seed", "provider": "LBMA", "timestamp": "1985-01-14 12:00:00"}, {"spot": 302.5, "metal": "Gold", "source": "seed", "provider": "LBMA", "timestamp": "1985-01-15 12:00:00"}, {"spot": 5.989, "metal": "Silver", "source": "seed", "provider": "LBMA", "timestamp": "1985-01-15 12:00:00"}, {"spot": 302.45, "metal": "Gold", "source": "seed", "provider": "LBMA", "timestamp": "1985-01-16 12:00:00"}, {"spot": 6.015, "metal": "Silver", "source": "seed", "provider": "LBMA", "timestamp": "1985-01-16 12:00:00"}, {"spot": 305.8, "metal": "Gold", "source": "seed", "provider": "LBMA", "timestamp": "1985-01-17 12:00:00"}, {"spot": 6.18, "metal": "Silver", "source": "seed", "provider": "LBMA", "timestamp": "1985-01-17 12:00:00"}, {"spot": 306.9, "metal": "Gold", "source": "seed", "provider": "LBMA", "timestamp": "1985-01-18 12:00:00"}, {"spot": 6.259, "metal": "Silver", "source": "seed", "provider": "LBMA", "timestamp": "1985-01-18 12:00:00"}, {"spot": 307.0, "metal": "Gold", "source": "seed", "provider": "LBMA", "timestamp": "1985-01-21 12:00:00"}, {"spot": 6.206, "metal": "Silver", "source": "seed", "provider": "LBMA", "timestamp": "1985-01-21 12:00:00"}, {"spot": 306.85, "metal": "Gold", "source": "seed", "provider": "LBMA", "timestamp": "1985-01-22 12:00:00"}, {"spot": 6.25, "metal": "Silver", "source": "seed", "provider": "LBMA", "timestamp": "1985-01-22 12:00:00"}, {"spot": 302.15, "metal": "Gold", "source": "seed", "provider": "LBMA", "timestamp": "1985-01-23 12:00:00"}, {"spot": 6.045, "metal": "Silver", "source": "seed", "provider": "LBMA", "timestamp": "1985-01-23 12:00:00"}, {"spot": 301.9, "metal": "Gold", "source": "seed", "provider": "LBMA", "timestamp": "1985-01-24 12:00:00"}, {"spot": 5.99, "metal": "Silver", "source": "seed", "provider": "LBMA", "timestamp": "1985-01-24 12:00:00"}, {"spot": 299.25, "metal": "Gold", "source": "seed", "provider": "LBMA", "timestamp": "1985-01-25 12:00:00"}, {"spot": 5.946, "metal": "Silver", "source": "seed", "provider": "LBMA", "timestamp": "1985-01-25 12:00:00"}, {"spot": 298.6, "metal": "Gold", "source": "seed", "provider": "LBMA", "timestamp": "1985-01-28 12:00:00"}, {"spot": 5.946, "metal": "Silver", "source": "seed", "provider": "LBMA", "timestamp": "1985-01-28 12:00:00"}, {"spot": 303.5, "metal": "Gold", "source": "seed", "provider": "LBMA", "timestamp": "1985-01-29 12:00:00"}, {"spot": 6.239, "metal": "Silver", "source": "seed", "provider": "LBMA", "timestamp": "1985-01-29 12:00:00"}, {"spot": 303.0, "metal": "Gold", "source": "seed", "provider": "LBMA", "timestamp": "1985-01-30 12:00:00"}, {"spot": 6.167, "metal": "Silver", "source": "seed", "provider": "LBMA", "timestamp": "1985-01-30 12:00:00"}, {"spot": 304.9, "metal": "Gold", "source": "seed", "provider": "LBMA", "timestamp": "1985-01-31 12:00:00"}, {"spot": 6.33, "metal": "Silver", "source": "seed", "provider": "LBMA", "timestamp": "1985-01-31 12:00:00"}, {"spot": 304.8, "metal": "Gold", "source": "seed", "provider": "LBMA", "timestamp": "1985-02-01 12:00:00"}, {"spot": 6.295, "metal": "Silver", "source": "seed", "provider": "LBMA", "timestamp": "1985-02-01 12:00:00"}, {"spot": 301.25, "metal": "Gold", "source": "seed", "provider": "LBMA", "timestamp": "1985-02-04 12:00:00"}, {"spot": 6.139, "metal": "Silver", "source": "seed", "provider": "LBMA", "timestamp": "1985-02-04 12:00:00"}, {"spot": 301.75, "metal": "Gold", "source": "seed", "provider": "LBMA", "timestamp": "1985-02-05 12:00:00"}, {"spot": 6.145, "metal": "Silver", "source": "seed", "provider": "LBMA", "timestamp": "1985-02-05 12:00:00"}, {"spot": 303.45, "metal": "Gold", "source": "seed", "provider": "LBMA", "timestamp": "1985-02-06 12:00:00"}, {"spot": 6.2, "metal": "Silver", "source": "seed", "provider": "LBMA", "timestamp": "1985-02-06 12:00:00"}, {"spot": 302.5, "metal": "Gold", "source": "seed", "provider": "LBMA", "timestamp": "1985-02-07 12:00:00"}, {"spot": 6.151, "metal": "Silver", "source": "seed", "provider": "LBMA", "timestamp": "1985-02-07 12:00:00"}, {"spot": 300.6, "metal": "Gold", "source": "seed", "provider": "LBMA", "timestamp": "1985-02-08 12:00:00"}, {"spot": 6.135, "metal": "Silver", "source": "seed", "provider": "LBMA", "timestamp": "1985-02-08 12:00:00"}, {"spot": 300.0, "metal": "Gold", "source": "seed", "provider": "LBMA", "timestamp": "1985-02-11 12:00:00"}, {"spot": 6.08, "metal": "Silver", "source": "seed", "provider": "LBMA", "timestamp": "1985-02-11 12:00:00"}, {"spot": 303.45, "metal": "Gold", "source": "seed", "provider": "LBMA", "timestamp": "1985-02-12 12:00:00"}, {"spot": 6.217, "metal": "Silver", "source": "seed", "provider": "LBMA", "timestamp": "1985-02-12 12:00:00"}, {"spot": 302.8, "metal": "Gold", "source": "seed", "provider": "LBMA", "timestamp": "1985-02-13 12:00:00"}, {"spot": 6.206, "metal": "Silver", "source": "seed", "provider": "LBMA", "timestamp": "1985-02-13 12:00:00"}, {"spot": 303.4, "metal": "Gold", "source": "seed", "provider": "LBMA", "timestamp": "1985-02-14 12:00:00"}, {"spot": 6.297, "metal": "Silver", "source": "seed", "provider": "LBMA", "timestamp": "1985-02-14 12:00:00"}, {"spot": 304.9, "metal": "Gold", "source": "seed", "provider": "LBMA", "timestamp": "1985-02-15 12:00:00"}, {"spot": 6.32, "metal": "Silver", "source": "seed", "provider": "LBMA", "timestamp": "1985-02-15 12:00:00"}, {"spot": 314.95, "metal": "Gold", "source": "seed", "provider": "LBMA", "timestamp": "1985-02-18 12:00:00"}, {"spot": 6.27, "metal": "Silver", "source": "seed", "provider": "LBMA", "timestamp": "1985-02-18 12:00:00"}, {"spot": 302.9, "metal": "Gold", "source": "seed", "provider": "LBMA", "timestamp": "1985-02-19 12:00:00"}, {"spot": 6.218, "metal": "Silver", "source": "seed", "provider": "LBMA", "timestamp": "1985-02-19 12:00:00"}, {"spot": 302.85, "metal": "Gold", "source": "seed", "provider": "LBMA", "timestamp": "1985-02-20 12:00:00"}, {"spot": 6.23, "metal": "Silver", "source": "seed", "provider": "LBMA", "timestamp": "1985-02-20 12:00:00"}, {"spot": 302.0, "metal": "Gold", "source": "seed", "provider": "LBMA", "timestamp": "1985-02-21 12:00:00"}, {"spot": 6.166, "metal": "Silver", "source": "seed", "provider": "LBMA", "timestamp": "1985-02-21 12:00:00"}, {"spot": 298.8, "metal": "Gold", "source": "seed", "provider": "LBMA", "timestamp": "1985-02-22 12:00:00"}, {"spot": 6.0, "metal": "Silver", "source": "seed", "provider": "LBMA", "timestamp": "1985-02-22 12:00:00"}, {"spot": 290.0, "metal": "Gold", "source": "seed", "provider": "LBMA", "timestamp": "1985-02-25 12:00:00"}, {"spot": 5.45, "metal": "Silver", "source": "seed", "provider": "LBMA", "timestamp": "1985-02-25 12:00:00"}, {"spot": 285.0, "metal": "Gold", "source": "seed", "provider": "LBMA", "timestamp": "1985-02-26 12:00:00"}, {"spot": 5.58, "metal": "Silver", "source": "seed", "provider": "LBMA", "timestamp": "1985-02-26 12:00:00"}, {"spot": 290.75, "metal": "Gold", "source": "seed", "provider": "LBMA", "timestamp": "1985-02-27 12:00:00"}, {"spot": 5.771, "metal": "Silver", "source": "seed", "provider": "LBMA", "timestamp": "1985-02-27 12:00:00"}, {"spot": 290.5, "metal": "Gold", "source": "seed", "provider": "LBMA", "timestamp": "1985-02-28 12:00:00"}, {"spot": 5.715, "metal": "Silver", "source": "seed", "provider": "LBMA", "timestamp": "1985-02-28 12:00:00"}, {"spot": 288.1, "metal": "Gold", "source": "seed", "provider": "LBMA", "timestamp": "1985-03-01 12:00:00"}, {"spot": 5.605, "metal": "Silver", "source": "seed", "provider": "LBMA", "timestamp": "1985-03-01 12:00:00"}, {"spot": 288.3, "metal": "Gold", "source": "seed", "provider": "LBMA", "timestamp": "1985-03-04 12:00:00"}, {"spot": 5.64, "metal": "Silver", "source": "seed", "provider": "LBMA", "timestamp": "1985-03-04 12:00:00"}, {"spot": 288.85, "metal": "Gold", "source": "seed", "provider": "LBMA", "timestamp": "1985-03-05 12:00:00"}, {"spot": 5.661, "metal": "Silver", "source": "seed", "provider": "LBMA", "timestamp": "1985-03-05 12:00:00"}, {"spot": 286.7, "metal": "Gold", "source": "seed", "provider": "LBMA", "timestamp": "1985-03-06 12:00:00"}, {"spot": 5.622, "metal": "Silver", "source": "seed", "provider": "LBMA", "timestamp": "1985-03-06 12:00:00"}, {"spot": 289.3, "metal": "Gold", "source": "seed", "provider": "LBMA", "timestamp": "1985-03-07 12:00:00"}, {"spot": 5.68, "metal": "Silver", "source": "seed", "provider": "LBMA", "timestamp": "1985-03-07 12:00:00"}, {"spot": 289.0, "metal": "Gold", "source": "seed", "provider": "LBMA", "timestamp": "1985-03-08 12:00:00"}, {"spot": 5.675, "metal": "Silver", "source": "seed", "provider": "LBMA", "timestamp": "1985-03-08 12:00:00"}, {"spot": 290.25, "metal": "Gold", "source": "seed", "provider": "LBMA", "timestamp": "1985-03-11 12:00:00"}, {"spot": 5.643, "metal": "Silver", "source": "seed", "provider": "LBMA", "timestamp": "1985-03-11 12:00:00"}, {"spot": 288.75, "metal": "Gold", "source": "seed", "provider": "LBMA", "timestamp": "1985-03-12 12:00:00"}, {"spot": 5.516, "metal": "Silver", "source": "seed", "provider": "LBMA", "timestamp": "1985-03-12 12:00:00"}, {"spot": 290.1, "metal": "Gold", "source": "seed", "provider": "LBMA", "timestamp": "1985-03-13 12:00:00"}, {"spot": 5.57, "metal": "Silver", "source": "seed", "provider": "LBMA", "timestamp": "1985-03-13 12:00:00"}, {"spot": 290.25, "metal": "Gold", "source": "seed", "provider": "LBMA", "timestamp": "1985-03-14 12:00:00"}, {"spot": 5.657, "metal": "Silver", "source": "seed", "provider": "LBMA", "timestamp": "1985-03-14 12:00:00"}, {"spot": 289.9, "metal": "Gold", "source": "seed", "provider": "LBMA", "timestamp": "1985-03-15 12:00:00"}, {"spot": 5.635, "metal": "Silver", "source": "seed", "provider": "LBMA", "timestamp": "1985-03-15 12:00:00"}, {"spot": 293.7, "metal": "Gold", "source": "seed", "provider": "LBMA", "timestamp": "1985-03-18 12:00:00"}, {"spot": 5.71, "metal": "Silver", "source": "seed", "provider": "LBMA", "timestamp": "1985-03-18 12:00:00"}, {"spot": 307.25, "metal": "Gold", "source": "seed", "provider": "LBMA", "timestamp": "1985-03-19 12:00:00"}, {"spot": 6.042, "metal": "Silver", "source": "seed", "provider": "LBMA", "timestamp": "1985-03-19 12:00:00"}, {"spot": 333.25, "metal": "Gold", "source": "seed", "provider": "LBMA", "timestamp": "1985-03-20 12:00:00"}, {"spot": 6.46, "metal": "Silver", "source": "seed", "provider": "LBMA", "timestamp": "1985-03-20 12:00:00"}, {"spot": 312.5, "metal": "Gold", "source": "seed", "provider": "LBMA", "timestamp": "1985-03-21 12:00:00"}, {"spot": 6.109, "metal": "Silver", "source": "seed", "provider": "LBMA", "timestamp": "1985-03-21 12:00:00"}, {"spot": 320.75, "metal": "Gold", "source": "seed", "provider": "LBMA", "timestamp": "1985-03-22 12:00:00"}, {"spot": 6.39, "metal": "Silver", "source": "seed", "provider": "LBMA", "timestamp": "1985-03-22 12:00:00"}, {"spot": 315.9, "metal": "Gold", "source": "seed", "provider": "LBMA", "timestamp": "1985-03-25 12:00:00"}, {"spot": 6.305, "metal": "Silver", "source": "seed", "provider": "LBMA", "timestamp": "1985-03-25 12:00:00"}, {"spot": 316.0, "metal": "Gold", "source": "seed", "provider": "LBMA", "timestamp": "1985-03-26 12:00:00"}, {"spot": 6.265, "metal": "Silver", "source": "seed", "provider": "LBMA", "timestamp": "1985-03-26 12:00:00"}, {"spot": 329.9, "metal": "Gold", "source": "seed", "provider": "LBMA", "timestamp": "1985-03-27 12:00:00"}, {"spot": 6.589, "metal": "Silver", "source": "seed", "provider": "LBMA", "timestamp": "1985-03-27 12:00:00"}, {"spot": 328.75, "metal": "Gold", "source": "seed", "provider": "LBMA", "timestamp": "1985-03-28 12:00:00"}, {"spot": 6.565, "metal": "Silver", "source": "seed", "provider": "LBMA", "timestamp": "1985-03-28 12:00:00"}, {"spot": 329.8, "metal": "Gold", "source": "seed", "provider": "LBMA", "timestamp": "1985-03-29 12:00:00"}, {"spot": 6.66, "metal": "Silver", "source": "seed", "provider": "LBMA", "timestamp": "1985-03-29 12:00:00"}, {"spot": 324.65, "metal": "Gold", "source": "seed", "provider": "LBMA", "timestamp": "1985-04-01 12:00:00"}, {"spot": 6.52, "metal": "Silver", "source": "seed", "provider": "LBMA", "timestamp": "1985-04-01 12:00:00"}, {"spot": 317.0, "metal": "Gold", "source": "seed", "provider": "LBMA", "timestamp": "1985-04-02 12:00:00"}, {"spot": 6.42, "metal": "Silver", "source": "seed", "provider": "LBMA", "timestamp": "1985-04-02 12:00:00"}, {"spot": 321.1, "metal": "Gold", "source": "seed", "provider": "LBMA", "timestamp": "1985-04-03 12:00:00"}, {"spot": 6.497, "metal": "Silver", "source": "seed", "provider": "LBMA", "timestamp": "1985-04-03 12:00:00"}, {"spot": 317.0, "metal": "Gold", "source": "seed", "provider": "LBMA", "timestamp": "1985-04-04 12:00:00"}, {"spot": 6.39, "metal": "Silver", "source": "seed", "provider": "LBMA", "timestamp": "1985-04-04 12:00:00"}, {"spot": 323.1, "metal": "Gold", "source": "seed", "provider": "LBMA", "timestamp": "1985-04-09 12:00:00"}, {"spot": 6.628, "metal": "Silver", "source": "seed", "provider": "LBMA", "timestamp": "1985-04-09 12:00:00"}, {"spot": 323.3, "metal": "Gold", "source": "seed", "provider": "LBMA", "timestamp": "1985-04-10 12:00:00"}, {"spot": 6.635, "metal": "Silver", "source": "seed", "provider": "LBMA", "timestamp": "1985-04-10 12:00:00"}, {"spot": 329.0, "metal": "Gold", "source": "seed", "provider": "LBMA", "timestamp": "1985-04-11 12:00:00"}, {"spot": 6.678, "metal": "Silver", "source": "seed", "provider": "LBMA", "timestamp": "1985-04-11 12:00:00"}, {"spot": 331.25, "metal": "Gold", "source": "seed", "provider": "LBMA", "timestamp": "1985-04-12 12:00:00"}, {"spot": 6.665, "metal": "Silver", "source": "seed", "provider": "LBMA", "timestamp": "1985-04-12 12:00:00"}, {"spot": 330.3, "metal": "Gold", "source": "seed", "provider": "LBMA", "timestamp": "1985-04-15 12:00:00"}, {"spot": 6.75, "metal": "Silver", "source": "seed", "provider": "LBMA", "timestamp": "1985-04-15 12:00:00"}, {"spot": 331.5, "metal": "Gold", "source": "seed", "provider": "LBMA", "timestamp": "1985-04-16 12:00:00"}, {"spot": 6.635, "metal": "Silver", "source": "seed", "provider": "LBMA", "timestamp": "1985-04-16 12:00:00"}, {"spot": 327.0, "metal": "Gold", "source": "seed", "provider": "LBMA", "timestamp": "1985-04-17 12:00:00"}, {"spot": 6.451, "metal": "Silver", "source": "seed", "provider": "LBMA", "timestamp": "1985-04-17 12:00:00"}, {"spot": 325.5, "metal": "Gold", "source": "seed", "provider": "LBMA", "timestamp": "1985-04-18 12:00:00"}, {"spot": 6.438, "metal": "Silver", "source": "seed", "provider": "LBMA", "timestamp": "1985-04-18 12:00:00"}, {"spot": 327.7, "metal": "Gold", "source": "seed", "provider": "LBMA", "timestamp": "1985-04-19 12:00:00"}, {"spot": 6.402, "metal": "Silver", "source": "seed", "provider": "LBMA", "timestamp": "1985-04-19 12:00:00"}, {"spot": 328.1, "metal": "Gold", "source": "seed", "provider": "LBMA", "timestamp": "1985-04-22 12:00:00"}, {"spot": 6.441, "metal": "Silver", "source": "seed", "provider": "LBMA", "timestamp": "1985-04-22 12:00:00"}, {"spot": 326.0, "metal": "Gold", "source": "seed", "provider": "LBMA", "timestamp": "1985-04-23 12:00:00"}, {"spot": 6.356, "metal": "Silver", "source": "seed", "provider": "LBMA", "timestamp": "1985-04-23 12:00:00"}, {"spot": 322.6, "metal": "Gold", "source": "seed", "provider": "LBMA", "timestamp": "1985-04-24 12:00:00"}, {"spot": 6.124, "metal": "Silver", "source": "seed", "provider": "LBMA", "timestamp": "1985-04-24 12:00:00"}, {"spot": 322.4, "metal": "Gold", "source": "seed", "provider": "LBMA", "timestamp": "1985-04-25 12:00:00"}, {"spot": 6.185, "metal": "Silver", "source": "seed", "provider": "LBMA", "timestamp": "1985-04-25 12:00:00"}, {"spot": 322.5, "metal": "Gold", "source": "seed", "provider": "LBMA", "timestamp": "1985-04-26 12:00:00"}, {"spot": 6.24, "metal": "Silver", "source": "seed", "provider": "LBMA", "timestamp": "1985-04-26 12:00:00"}, {"spot": 323.0, "metal": "Gold", "source": "seed", "provider": "LBMA", "timestamp": "1985-04-29 12:00:00"}, {"spot": 6.242, "metal": "Silver", "source": "seed", "provider": "LBMA", "timestamp": "1985-04-29 12:00:00"}, {"spot": 324.65, "metal": "Gold", "source": "seed", "provider": "LBMA", "timestamp": "1985-04-30 12:00:00"}, {"spot": 6.322, "metal": "Silver", "source": "seed", "provider": "LBMA", "timestamp": "1985-04-30 12:00:00"}, {"spot": 315.6, "metal": "Gold", "source": "seed", "provider": "LBMA", "timestamp": "1985-05-01 12:00:00"}, {"spot": 6.15, "metal": "Silver", "source": "seed", "provider": "LBMA", "timestamp": "1985-05-01 12:00:00"}, {"spot": 314.25, "metal": "Gold", "source": "seed", "provider": "LBMA", "timestamp": "1985-05-02 12:00:00"}, {"spot": 6.15, "metal": "Silver", "source": "seed", "provider": "LBMA", "timestamp": "1985-05-02 12:00:00"}, {"spot": 313.7, "metal": "Gold", "source": "seed", "provider": "LBMA", "timestamp": "1985-05-03 12:00:00"}, {"spot": 6.16, "metal": "Silver", "source": "seed", "provider": "LBMA", "timestamp": "1985-05-03 12:00:00"}, {"spot": 311.25, "metal": "Gold", "source": "seed", "provider": "LBMA", "timestamp": "1985-05-07 12:00:00"}, {"spot": 6.145, "metal": "Silver", "source": "seed", "provider": "LBMA", "timestamp": "1985-05-07 12:00:00"}, {"spot": 313.35, "metal": "Gold", "source": "seed", "provider": "LBMA", "timestamp": "1985-05-08 12:00:00"}, {"spot": 6.251, "metal": "Silver", "source": "seed", "provider": "LBMA", "timestamp": "1985-05-08 12:00:00"}, {"spot": 314.5, "metal": "Gold", "source": "seed", "provider": "LBMA", "timestamp": "1985-05-09 12:00:00"}, {"spot": 6.35, "metal": "Silver", "source": "seed", "provider": "LBMA", "timestamp": "1985-05-09 12:00:00"}, {"spot": 313.55, "metal": "Gold", "source": "seed", "provider": "LBMA", "timestamp": "1985-05-10 12:00:00"}, {"spot": 6.292, "metal": "Silver", "source": "seed", "provider": "LBMA", "timestamp": "1985-05-10 12:00:00"}, {"spot": 316.75, "metal": "Gold", "source": "seed", "provider": "LBMA", "timestamp": "1985-05-13 12:00:00"}, {"spot": 6.355, "metal": "Silver", "source": "seed", "provider": "LBMA", "timestamp": "1985-05-13 12:00:00"}, {"spot": 324.75, "metal": "Gold", "source": "seed", "provider": "LBMA", "timestamp": "1985-05-14 12:00:00"}, {"spot": 6.535, "metal": "Silver", "source": "seed", "provider": "LBMA", "timestamp": "1985-05-14 12:00:00"}, {"spot": 322.85, "metal": "Gold", "source": "seed", "provider": "LBMA", "timestamp": "1985-05-15 12:00:00"}, {"spot": 6.491, "metal": "Silver", "source": "seed", "provider": "LBMA", "timestamp": "1985-05-15 12:00:00"}, {"spot": 320.4, "metal": "Gold", "source": "seed", "provider": "LBMA", "timestamp": "1985-05-16 12:00:00"}, {"spot": 6.485, "metal": "Silver", "source": "seed", "provider": "LBMA", "timestamp": "1985-05-16 12:00:00"}, {"spot": 319.8, "metal": "Gold", "source": "seed", "provider": "LBMA", "timestamp": "1985-05-17 12:00:00"}, {"spot": 6.45, "metal": "Silver", "source": "seed", "provider": "LBMA", "timestamp": "1985-05-17 12:00:00"}, {"spot": 323.65, "metal": "Gold", "source": "seed", "provider": "LBMA", "timestamp": "1985-05-20 12:00:00"}, {"spot": 6.558, "metal": "Silver", "source": "seed", "provider": "LBMA", "timestamp": "1985-05-20 12:00:00"}, {"spot": 316.5, "metal": "Gold", "source": "seed", "provider": "LBMA", "timestamp": "1985-05-21 12:00:00"}, {"spot": 6.215, "metal": "Silver", "source": "seed", "provider": "LBMA", "timestamp": "1985-05-21 12:00:00"}, {"spot": 317.4, "metal": "Gold", "source": "seed", "provider": "LBMA", "timestamp": "1985-05-22 12:00:00"}, {"spot": 6.2, "metal": "Silver", "source": "seed", "provider": "LBMA", "timestamp": "1985-05-22 12:00:00"}, {"spot": 316.4, "metal": "Gold", "source": "seed", "provider": "LBMA", "timestamp": "1985-05-23 12:00:00"}, {"spot": 6.155, "metal": "Silver", "source": "seed", "provider": "LBMA", "timestamp": "1985-05-23 12:00:00"}, {"spot": 316.35, "metal": "Gold", "source": "seed", "provider": "LBMA", "timestamp": "1985-05-24 12:00:00"}, {"spot": 6.147, "metal": "Silver", "source": "seed", "provider": "LBMA", "timestamp": "1985-05-24 12:00:00"}, {"spot": 313.9, "metal": "Gold", "source": "seed", "provider": "LBMA", "timestamp": "1985-05-28 12:00:00"}, {"spot": 6.1, "metal": "Silver", "source": "seed", "provider": "LBMA", "timestamp": "1985-05-28 12:00:00"}, {"spot": 311.2, "metal": "Gold", "source": "seed", "provider": "LBMA", "timestamp": "1985-05-29 12:00:00"}, {"spot": 6.001, "metal": "Silver", "source": "seed", "provider": "LBMA", "timestamp": "1985-05-29 12:00:00"}, {"spot": 315.0, "metal": "Gold", "source": "seed", "provider": "LBMA", "timestamp": "1985-05-30 12:00:00"}, {"spot": 6.159, "metal": "Silver", "source": "seed", "provider": "LBMA", "timestamp": "1985-05-30 12:00:00"}, {"spot": 313.15, "metal": "Gold", "source": "seed", "provider": "LBMA", "timestamp": "1985-05-31 12:00:00"}, {"spot": 6.085, "metal": "Silver", "source": "seed", "provider": "LBMA", "timestamp": "1985-05-31 12:00:00"}, {"spot": 316.85, "metal": "Gold", "source": "seed", "provider": "LBMA", "timestamp": "1985-06-03 12:00:00"}, {"spot": 6.209, "metal": "Silver", "source": "seed", "provider": "LBMA", "timestamp": "1985-06-03 12:00:00"}, {"spot": 316.25, "metal": "Gold", "source": "seed", "provider": "LBMA", "timestamp": "1985-06-04 12:00:00"}, {"spot": 6.108, "metal": "Silver", "source": "seed", "provider": "LBMA", "timestamp": "1985-06-04 12:00:00"}, {"spot": 314.75, "metal": "Gold", "source": "seed", "provider": "LBMA", "timestamp": "1985-06-05 12:00:00"}, {"spot": 6.06, "metal": "Silver", "source": "seed", "provider": "LBMA", "timestamp": "1985-06-05 12:00:00"}, {"spot": 314.9, "metal": "Gold", "source": "seed", "provider": "LBMA", "timestamp": "1985-06-06 12:00:00"}, {"spot": 6.119, "metal": "Silver", "source": "seed", "provider": "LBMA", "timestamp": "1985-06-06 12:00:00"}, {"spot": 315.0, "metal": "Gold", "source": "seed", "provider": "LBMA", "timestamp": "1985-06-07 12:00:00"}, {"spot": 6.103, "metal": "Silver", "source": "seed", "provider": "LBMA", "timestamp": "1985-06-07 12:00:00"}, {"spot": 310.75, "metal": "Gold", "source": "seed", "provider": "LBMA", "timestamp": "1985-06-10 12:00:00"}, {"spot": 6.084, "metal": "Silver", "source": "seed", "provider": "LBMA", "timestamp": "1985-06-10 12:00:00"}, {"spot": 313.25, "metal": "Gold", "source": "seed", "provider": "LBMA", "timestamp": "1985-06-11 12:00:00"}, {"spot": 6.138, "metal": "Silver", "source": "seed", "provider": "LBMA", "timestamp": "1985-06-11 12:00:00"}, {"spot": 313.75, "metal": "Gold", "source": "seed", "provider": "LBMA", "timestamp": "1985-06-12 12:00:00"}, {"spot": 6.143, "metal": "Silver", "source": "seed", "provider": "LBMA", "timestamp": "1985-06-12 12:00:00"}, {"spot": 314.1, "metal": "Gold", "source": "seed", "provider": "LBMA", "timestamp": "1985-06-13 12:00:00"}, {"spot": 6.16, "metal": "Silver", "source": "seed", "provider": "LBMA", "timestamp": "1985-06-13 12:00:00"}, {"spot": 315.75, "metal": "Gold", "source": "seed", "provider": "LBMA", "timestamp": "1985-06-14 12:00:00"}, {"spot": 6.237, "metal": "Silver", "source": "seed", "provider": "LBMA", "timestamp": "1985-06-14 12:00:00"}, {"spot": 317.25, "metal": "Gold", "source": "seed", "provider": "LBMA", "timestamp": "1985-06-17 12:00:00"}, {"spot": 6.21, "metal": "Silver", "source": "seed", "provider": "LBMA", "timestamp": "1985-06-17 12:00:00"}, {"spot": 321.65, "metal": "Gold", "source": "seed", "provider": "LBMA", "timestamp": "1985-06-18 12:00:00"}, {"spot": 6.304, "metal": "Silver", "source": "seed", "provider": "LBMA", "timestamp": "1985-06-18 12:00:00"}, {"spot": 325.2, "metal": "Gold", "source": "seed", "provider": "LBMA", "timestamp": "1985-06-19 12:00:00"}, {"spot": 6.42, "metal": "Silver", "source": "seed", "provider": "LBMA", "timestamp": "1985-06-19 12:00:00"}, {"spot": 322.0, "metal": "Gold", "source": "seed", "provider": "LBMA", "timestamp": "1985-06-20 12:00:00"}, {"spot": 6.289, "metal": "Silver", "source": "seed", "provider": "LBMA", "timestamp": "1985-06-20 12:00:00"}, {"spot": 315.25, "metal": "Gold", "source": "seed", "provider": "LBMA", "timestamp": "1985-06-21 12:00:00"}, {"spot": 6.113, "metal": "Silver", "source": "seed", "provider": "LBMA", "timestamp": "1985-06-21 12:00:00"}, {"spot": 314.1, "metal": "Gold", "source": "seed", "provider": "LBMA", "timestamp": "1985-06-24 12:00:00"}, {"spot": 6.109, "metal": "Silver", "source": "seed", "provider": "LBMA", "timestamp": "1985-06-24 12:00:00"}, {"spot": 315.9, "metal": "Gold", "source": "seed", "provider": "LBMA", "timestamp": "1985-06-25 12:00:00"}, {"spot": 6.148, "metal": "Silver", "source": "seed", "provider": "LBMA", "timestamp": "1985-06-25 12:00:00"}, {"spot": 316.5, "metal": "Gold", "source": "seed", "provider": "LBMA", "timestamp": "1985-06-26 12:00:00"}, {"spot": 6.12, "metal": "Silver", "source": "seed", "provider": "LBMA", "timestamp": "1985-06-26 12:00:00"}, {"spot": 316.25, "metal": "Gold", "source": "seed", "provider": "LBMA", "timestamp": "1985-06-27 12:00:00"}, {"spot": 6.13, "metal": "Silver", "source": "seed", "provider": "LBMA", "timestamp": "1985-06-27 12:00:00"}, {"spot": 316.5, "metal": "Gold", "source": "seed", "provider": "LBMA", "timestamp": "1985-06-28 12:00:00"}, {"spot": 6.11, "metal": "Silver", "source": "seed", "provider": "LBMA", "timestamp": "1985-06-28 12:00:00"}, {"spot": 315.35, "metal": "Gold", "source": "seed", "provider": "LBMA", "timestamp": "1985-07-01 12:00:00"}, {"spot": 6.095, "metal": "Silver", "source": "seed", "provider": "LBMA", "timestamp": "1985-07-01 12:00:00"}, {"spot": 310.85, "metal": "Gold", "source": "seed", "provider": "LBMA", "timestamp": "1985-07-02 12:00:00"}, {"spot": 5.939, "metal": "Silver", "source": "seed", "provider": "LBMA", "timestamp": "1985-07-02 12:00:00"}, {"spot": 310.4, "metal": "Gold", "source": "seed", "provider": "LBMA", "timestamp": "1985-07-03 12:00:00"}, {"spot": 5.888, "metal": "Silver", "source": "seed", "provider": "LBMA", "timestamp": "1985-07-03 12:00:00"}, {"spot": 310.7, "metal": "Gold", "source": "seed", "provider": "LBMA", "timestamp": "1985-07-04 12:00:00"}, {"spot": 5.92, "metal": "Silver", "source": "seed", "provider": "LBMA", "timestamp": "1985-07-04 12:00:00"}, {"spot": 310.9, "metal": "Gold", "source": "seed", "provider": "LBMA", "timestamp": "1985-07-05 12:00:00"}, {"spot": 5.907, "metal": "Silver", "source": "seed", "provider": "LBMA", "timestamp": "1985-07-05 12:00:00"}, {"spot": 312.2, "metal": "Gold", "source": "seed", "provider": "LBMA", "timestamp": "1985-07-08 12:00:00"}, {"spot": 5.931, "metal": "Silver", "source": "seed", "provider": "LBMA", "timestamp": "1985-07-08 12:00:00"}, {"spot": 314.8, "metal": "Gold", "source": "seed", "provider": "LBMA", "timestamp": "1985-07-09 12:00:00"}, {"spot": 6.046, "metal": "Silver", "source": "seed", "provider": "LBMA", "timestamp": "1985-07-09 12:00:00"}, {"spot": 314.7, "metal": "Gold", "source": "seed", "provider": "LBMA", "timestamp": "1985-07-10 12:00:00"}, {"spot": 6.045, "metal": "Silver", "source": "seed", "provider": "LBMA", "timestamp": "1985-07-10 12:00:00"}, {"spot": 313.8, "metal": "Gold", "source": "seed", "provider": "LBMA", "timestamp": "1985-07-11 12:00:00"}, {"spot": 5.985, "metal": "Silver", "source": "seed", "provider": "LBMA", "timestamp": "1985-07-11 12:00:00"}, {"spot": 315.05, "metal": "Gold", "source": "seed", "provider": "LBMA", "timestamp": "1985-07-12 12:00:00"}, {"spot": 6.04, "metal": "Silver", "source": "seed", "provider": "LBMA", "timestamp": "1985-07-12 12:00:00"}, {"spot": 317.15, "metal": "Gold", "source": "seed", "provider": "LBMA", "timestamp": "1985-07-15 12:00:00"}, {"spot": 6.08, "metal": "Silver", "source": "seed", "provider": "LBMA", "timestamp": "1985-07-15 12:00:00"}, {"spot": 316.8, "metal": "Gold", "source": "seed", "provider": "LBMA", "timestamp": "1985-07-16 12:00:00"}, {"spot": 6.1, "metal": "Silver", "source": "seed", "provider": "LBMA", "timestamp": "1985-07-16 12:00:00"}, {"spot": 321.7, "metal": "Gold", "source": "seed", "provider": "LBMA", "timestamp": "1985-07-17 12:00:00"}, {"spot": 6.245, "metal": "Silver", "source": "seed", "provider": "LBMA", "timestamp": "1985-07-17 12:00:00"}, {"spot": 322.25, "metal": "Gold", "source": "seed", "provider": "LBMA", "timestamp": "1985-07-18 12:00:00"}, {"spot": 6.208, "metal": "Silver", "source": "seed", "provider": "LBMA", "timestamp": "1985-07-18 12:00:00"}, {"spot": 319.0, "metal": "Gold", "source": "seed", "provider": "LBMA", "timestamp": "1985-07-19 12:00:00"}, {"spot": 6.123, "metal": "Silver", "source": "seed", "provider": "LBMA", "timestamp": "1985-07-19 12:00:00"}, {"spot": 317.4, "metal": "Gold", "source": "seed", "provider": "LBMA", "timestamp": "1985-07-22 12:00:00"}, {"spot": 6.125, "metal": "Silver", "source": "seed", "provider": "LBMA", "timestamp": "1985-07-22 12:00:00"}, {"spot": 322.75, "metal": "Gold", "source": "seed", "provider": "LBMA", "timestamp": "1985-07-23 12:00:00"}, {"spot": 6.158, "metal": "Silver", "source": "seed", "provider": "LBMA", "timestamp": "1985-07-23 12:00:00"}, {"spot": 318.5, "metal": "Gold", "source": "seed", "provider": "LBMA", "timestamp": "1985-07-24 12:00:00"}, {"spot": 6.092, "metal": "Silver", "source": "seed", "provider": "LBMA", "timestamp": "1985-07-24 12:00:00"}, {"spot": 319.4, "metal": "Gold", "source": "seed", "provider": "LBMA", "timestamp": "1985-07-25 12:00:00"}, {"spot": 6.098, "metal": "Silver", "source": "seed", "provider": "LBMA", "timestamp": "1985-07-25 12:00:00"}, {"spot": 317.6, "metal": "Gold", "source": "seed", "provider": "LBMA", "timestamp": "1985-07-26 12:00:00"}, {"spot": 6.075, "metal": "Silver", "source": "seed", "provider": "LBMA", "timestamp": "1985-07-26 12:00:00"}, {"spot": 323.0, "metal": "Gold", "source": "seed", "provider": "LBMA", "timestamp": "1985-07-29 12:00:00"}, {"spot": 6.234, "metal": "Silver", "source": "seed", "provider": "LBMA", "timestamp": "1985-07-29 12:00:00"}, {"spot": 323.25, "metal": "Gold", "source": "seed", "provider": "LBMA", "timestamp": "1985-07-30 12:00:00"}, {"spot": 6.255, "metal": "Silver", "source": "seed", "provider": "LBMA", "timestamp": "1985-07-30 12:00:00"}, {"spot": 328.1, "metal": "Gold", "source": "seed", "provider": "LBMA", "timestamp": "1985-07-31 12:00:00"}, {"spot": 6.335, "metal": "Silver", "source": "seed", "provider": "LBMA", "timestamp": "1985-07-31 12:00:00"}, {"spot": 326.75, "metal": "Gold", "source": "seed", "provider": "LBMA", "timestamp": "1985-08-01 12:00:00"}, {"spot": 6.25, "metal": "Silver", "source": "seed", "provider": "LBMA", "timestamp": "1985-08-01 12:00:00"}, {"spot": 319.65, "metal": "Gold", "source": "seed", "provider": "LBMA", "timestamp": "1985-08-02 12:00:00"}, {"spot": 6.13, "metal": "Silver", "source": "seed", "provider": "LBMA", "timestamp": "1985-08-02 12:00:00"}, {"spot": 323.0, "metal": "Gold", "source": "seed", "provider": "LBMA", "timestamp": "1985-08-05 12:00:00"}, {"spot": 6.182, "metal": "Silver", "source": "seed", "provider": "LBMA", "timestamp": "1985-08-05 12:00:00"}, {"spot": 321.4, "metal": "Gold", "source": "seed", "provider": "LBMA", "timestamp": "1985-08-06 12:00:00"}, {"spot": 6.138, "metal": "Silver", "source": "seed", "provider": "LBMA", "timestamp": "1985-08-06 12:00:00"}, {"spot": 320.65, "metal": "Gold", "source": "seed", "provider": "LBMA", "timestamp": "1985-08-07 12:00:00"}, {"spot": 6.11, "metal": "Silver", "source": "seed", "provider": "LBMA", "timestamp": "1985-08-07 12:00:00"}, {"spot": 322.9, "metal": "Gold", "source": "seed", "provider": "LBMA", "timestamp": "1985-08-08 12:00:00"}, {"spot": 6.146, "metal": "Silver", "source": "seed", "provider": "LBMA", "timestamp": "1985-08-08 12:00:00"}, {"spot": 322.4, "metal": "Gold", "source": "seed", "provider": "LBMA", "timestamp": "1985-08-09 12:00:00"}, {"spot": 6.125, "metal": "Silver", "source": "seed", "provider": "LBMA", "timestamp": "1985-08-09 12:00:00"}, {"spot": 326.6, "metal": "Gold", "source": "seed", "provider": "LBMA", "timestamp": "1985-08-12 12:00:00"}, {"spot": 6.27, "metal": "Silver", "source": "seed", "provider": "LBMA", "timestamp": "1985-08-12 12:00:00"}, {"spot": 328.5, "metal": "Gold", "source": "seed", "provider": "LBMA", "timestamp": "1985-08-13 12:00:00"}, {"spot": 6.33, "metal": "Silver", "source": "seed", "provider": "LBMA", "timestamp": "1985-08-13 12:00:00"}, {"spot": 326.2, "metal": "Gold", "source": "seed", "provider": "LBMA", "timestamp": "1985-08-14 12:00:00"}, {"spot": 6.26, "metal": "Silver", "source": "seed", "provider": "LBMA", "timestamp": "1985-08-14 12:00:00"}, {"spot": 328.9, "metal": "Gold", "source": "seed", "provider": "LBMA", "timestamp": "1985-08-15 12:00:00"}, {"spot": 6.303, "metal": "Silver", "source": "seed", "provider": "LBMA", "timestamp": "1985-08-15 12:00:00"}, {"spot": 335.4, "metal": "Gold", "source": "seed", "provider": "LBMA", "timestamp": "1985-08-16 12:00:00"}, {"spot": 6.348, "metal": "Silver", "source": "seed", "provider": "LBMA", "timestamp": "1985-08-16 12:00:00"}, {"spot": 339.25, "metal": "Gold", "source": "seed", "provider": "LBMA", "timestamp": "1985-08-19 12:00:00"}, {"spot": 6.387, "metal": "Silver", "source": "seed", "provider": "LBMA", "timestamp": "1985-08-19 12:00:00"}, {"spot": 335.5, "metal": "Gold", "source": "seed", "provider": "LBMA", "timestamp": "1985-08-20 12:00:00"}, {"spot": 6.26, "metal": "Silver", "source": "seed", "provider": "LBMA", "timestamp": "1985-08-20 12:00:00"}, {"spot": 335.75, "metal": "Gold", "source": "seed", "provider": "LBMA", "timestamp": "1985-08-21 12:00:00"}, {"spot": 6.245, "metal": "Silver", "source": "seed", "provider": "LBMA", "timestamp": "1985-08-21 12:00:00"}, {"spot": 337.6, "metal": "Gold", "source": "seed", "provider": "LBMA", "timestamp": "1985-08-22 12:00:00"}, {"spot": 6.3, "metal": "Silver", "source": "seed", "provider": "LBMA", "timestamp": "1985-08-22 12:00:00"}, {"spot": 333.6, "metal": "Gold", "source": "seed", "provider": "LBMA", "timestamp": "1985-08-23 12:00:00"}, {"spot": 6.215, "metal": "Silver", "source": "seed", "provider": "LBMA", "timestamp": "1985-08-23 12:00:00"}, {"spot": 335.25, "metal": "Gold", "source": "seed", "provider": "LBMA", "timestamp": "1985-08-27 12:00:00"}, {"spot": 6.304, "metal": "Silver", "source": "seed", "provider": "LBMA", "timestamp": "1985-08-27 12:00:00"}, {"spot": 339.3, "metal": "Gold", "source": "seed", "provider": "LBMA", "timestamp": "1985-08-28 12:00:00"}, {"spot": 6.398, "metal": "Silver", "source": "seed", "provider": "LBMA", "timestamp": "1985-08-28 12:00:00"}, {"spot": 338.4, "metal": "Gold", "source": "seed", "provider": "LBMA", "timestamp": "1985-08-29 12:00:00"}, {"spot": 6.3, "metal": "Silver", "source": "seed", "provider": "LBMA", "timestamp": "1985-08-29 12:00:00"}, {"spot": 335.75, "metal": "Gold", "source": "seed", "provider": "LBMA", "timestamp": "1985-08-30 12:00:00"}, {"spot": 6.247, "metal": "Silver", "source": "seed", "provider": "LBMA", "timestamp": "1985-08-30 12:00:00"}, {"spot": 335.45, "metal": "Gold", "source": "seed", "provider": "LBMA", "timestamp": "1985-09-02 12:00:00"}, {"spot": 6.223, "metal": "Silver", "source": "seed", "provider": "LBMA", "timestamp": "1985-09-02 12:00:00"}, {"spot": 332.7, "metal": "Gold", "source": "seed", "provider": "LBMA", "timestamp": "1985-09-03 12:00:00"}, {"spot": 6.193, "metal": "Silver", "source": "seed", "provider": "LBMA", "timestamp": "1985-09-03 12:00:00"}, {"spot": 325.0, "metal": "Gold", "source": "seed", "provider": "LBMA", "timestamp": "1985-09-04 12:00:00"}, {"spot": 6.098, "metal": "Silver", "source": "seed", "provider": "LBMA", "timestamp": "1985-09-04 12:00:00"}, {"spot": 326.0, "metal": "Gold", "source": "seed", "provider": "LBMA", "timestamp": "1985-09-05 12:00:00"}, {"spot": 6.08, "metal": "Silver", "source": "seed", "provider": "LBMA", "timestamp": "1985-09-05 12:00:00"}, {"spot": 318.75, "metal": "Gold", "source": "seed", "provider": "LBMA", "timestamp": "1985-09-06 12:00:00"}, {"spot": 6.002, "metal": "Silver", "source": "seed", "provider": "LBMA", "timestamp": "1985-09-06 12:00:00"}, {"spot": 320.2, "metal": "Gold", "source": "seed", "provider": "LBMA", "timestamp": "1985-09-09 12:00:00"}, {"spot": 6.06, "metal": "Silver", "source": "seed", "provider": "LBMA", "timestamp": "1985-09-09 12:00:00"}, {"spot": 320.0, "metal": "Gold", "source": "seed", "provider": "LBMA", "timestamp": "1985-09-10 12:00:00"}, {"spot": 6.029, "metal": "Silver", "source": "seed", "provider": "LBMA", "timestamp": "1985-09-10 12:00:00"}, {"spot": 322.0, "metal": "Gold", "source": "seed", "provider": "LBMA", "timestamp": "1985-09-11 12:00:00"}, {"spot": 6.045, "metal": "Silver", "source": "seed", "provider": "LBMA", "timestamp": "1985-09-11 12:00:00"}, {"spot": 318.0, "metal": "Gold", "source": "seed", "provider": "LBMA", "timestamp": "1985-09-12 12:00:00"}, {"spot": 5.975, "metal": "Silver", "source": "seed", "provider": "LBMA", "timestamp": "1985-09-12 12:00:00"}, {"spot": 321.75, "metal": "Gold", "source": "seed", "provider": "LBMA", "timestamp": "1985-09-13 12:00:00"}, {"spot": 6.053, "metal": "Silver", "source": "seed", "provider": "LBMA", "timestamp": "1985-09-13 12:00:00"}, {"spot": 318.85, "metal": "Gold", "source": "seed", "provider": "LBMA", "timestamp": "1985-09-16 12:00:00"}, {"spot": 5.997, "metal": "Silver", "source": "seed", "provider": "LBMA", "timestamp": "1985-09-16 12:00:00"}, {"spot": 318.7, "metal": "Gold", "source": "seed", "provider": "LBMA", "timestamp": "1985-09-17 12:00:00"}, {"spot": 6.007, "metal": "Silver", "source": "seed", "provider": "LBMA", "timestamp": "1985-09-17 12:00:00"}, {"spot": 315.5, "metal": "Gold", "source": "seed", "provider": "LBMA", "timestamp": "1985-09-18 12:00:00"}, {"spot": 5.886, "metal": "Silver", "source": "seed", "provider": "LBMA", "timestamp": "1985-09-18 12:00:00"}, {"spot": 315.9, "metal": "Gold", "source": "seed", "provider": "LBMA", "timestamp": "1985-09-19 12:00:00"}, {"spot": 5.932, "metal": "Silver", "source": "seed", "provider": "LBMA", "timestamp": "1985-09-19 12:00:00"}, {"spot": 319.2, "metal": "Gold", "source": "seed", "provider": "LBMA", "timestamp": "1985-09-20 12:00:00"}, {"spot": 6.0, "metal": "Silver", "source": "seed", "provider": "LBMA", "timestamp": "1985-09-20 12:00:00"}, {"spot": 328.1, "metal": "Gold", "source": "seed", "provider": "LBMA", "timestamp": "1985-09-23 12:00:00"}, {"spot": 6.165, "metal": "Silver", "source": "seed", "provider": "LBMA", "timestamp": "1985-09-23 12:00:00"}, {"spot": 328.4, "metal": "Gold", "source": "seed", "provider": "LBMA", "timestamp": "1985-09-24 12:00:00"}, {"spot": 6.173, "metal": "Silver", "source": "seed", "provider": "LBMA", "timestamp": "1985-09-24 12:00:00"}, {"spot": 328.7, "metal": "Gold", "source": "seed", "provider": "LBMA", "timestamp": "1985-09-25 12:00:00"}, {"spot": 6.14, "metal": "Silver", "source": "seed", "provider": "LBMA", "timestamp": "1985-09-25 12:00:00"}, {"spot": 330.4, "metal": "Gold", "source": "seed", "provider": "LBMA", "timestamp": "1985-09-26 12:00:00"}, {"spot": 6.157, "metal": "Silver", "source": "seed", "provider": "LBMA", "timestamp": "1985-09-26 12:00:00"}, {"spot": 328.95, "metal": "Gold", "source": "seed", "provider": "LBMA", "timestamp": "1985-09-27 12:00:00"}, {"spot": 6.062, "metal": "Silver", "source": "seed", "provider": "LBMA", "timestamp": "1985-09-27 12:00:00"}, {"spot": 326.5, "metal": "Gold", "source": "seed", "provider": "LBMA", "timestamp": "1985-09-30 12:00:00"}, {"spot": 6.054, "metal": "Silver", "source": "seed", "provider": "LBMA", "timestamp": "1985-09-30 12:00:00"}, {"spot": 323.15, "metal": "Gold", "source": "seed", "provider": "LBMA", "timestamp": "1985-10-01 12:00:00"}, {"spot": 6.0, "metal": "Silver", "source": "seed", "provider": "LBMA", "timestamp": "1985-10-01 12:00:00"}, {"spot": 324.75, "metal": "Gold", "source": "seed", "provider": "LBMA", "timestamp": "1985-10-02 12:00:00"}, {"spot": 6.037, "metal": "Silver", "source": "seed", "provider": "LBMA", "timestamp": "1985-10-02 12:00:00"}, {"spot": 324.35, "metal": "Gold", "source": "seed", "provider": "LBMA", "timestamp": "1985-10-03 12:00:00"}, {"spot": 6.087, "metal": "Silver", "source": "seed", "provider": "LBMA", "timestamp": "1985-10-03 12:00:00"}, {"spot": 330.55, "metal": "Gold", "source": "seed", "provider": "LBMA", "timestamp": "1985-10-04 12:00:00"}, {"spot": 6.36, "metal": "Silver", "source": "seed", "provider": "LBMA", "timestamp": "1985-10-04 12:00:00"}, {"spot": 326.25, "metal": "Gold", "source": "seed", "provider": "LBMA", "timestamp": "1985-10-07 12:00:00"}, {"spot": 6.25, "metal": "Silver", "source": "seed", "provider": "LBMA", "timestamp": "1985-10-07 12:00:00"}, {"spot": 326.1, "metal": "Gold", "source": "seed", "provider": "LBMA", "timestamp": "1985-10-08 12:00:00"}, {"spot": 6.26, "metal": "Silver", "source": "seed", "provider": "LBMA", "timestamp": "1985-10-08 12:00:00"}, {"spot": 326.95, "metal": "Gold", "source": "seed", "provider": "LBMA", "timestamp": "1985-10-09 12:00:00"}, {"spot": 6.283, "metal": "Silver", "source": "seed", "provider": "LBMA", "timestamp": "1985-10-09 12:00:00"}, {"spot": 325.55, "metal": "Gold", "source": "seed", "provider": "LBMA", "timestamp": "1985-10-10 12:00:00"}, {"spot": 6.23, "metal": "Silver", "source": "seed", "provider": "LBMA", "timestamp": "1985-10-10 12:00:00"}, {"spot": 325.8, "metal": "Gold", "source": "seed", "provider": "LBMA", "timestamp": "1985-10-11 12:00:00"}, {"spot": 6.222, "metal": "Silver", "source": "seed", "provider": "LBMA", "timestamp": "1985-10-11 12:00:00"}, {"spot": 326.6, "metal": "Gold", "source": "seed", "provider": "LBMA", "timestamp": "1985-10-14 12:00:00"}, {"spot": 6.222, "metal": "Silver", "source": "seed", "provider": "LBMA", "timestamp": "1985-10-14 12:00:00"}, {"spot": 326.85, "metal": "Gold", "source": "seed", "provider": "LBMA", "timestamp": "1985-10-15 12:00:00"}, {"spot": 6.257, "metal": "Silver", "source": "seed", "provider": "LBMA", "timestamp": "1985-10-15 12:00:00"}, {"spot": 325.9, "metal": "Gold", "source": "seed", "provider": "LBMA", "timestamp": "1985-10-16 12:00:00"}, {"spot": 6.225, "metal": "Silver", "source": "seed", "provider": "LBMA", "timestamp": "1985-10-16 12:00:00"}, {"spot": 324.6, "metal": "Gold", "source": "seed", "provider": "LBMA", "timestamp": "1985-10-17 12:00:00"}, {"spot": 6.126, "metal": "Silver", "source": "seed", "provider": "LBMA", "timestamp": "1985-10-17 12:00:00"}, {"spot": 326.25, "metal": "Gold", "source": "seed", "provider": "LBMA", "timestamp": "1985-10-18 12:00:00"}, {"spot": 6.157, "metal": "Silver", "source": "seed", "provider": "LBMA", "timestamp": "1985-10-18 12:00:00"}, {"spot": 326.5, "metal": "Gold", "source": "seed", "provider": "LBMA", "timestamp": "1985-10-21 12:00:00"}, {"spot": 6.164, "metal": "Silver", "source": "seed", "provider": "LBMA", "timestamp": "1985-10-21 12:00:00"}, {"spot": 325.9, "metal": "Gold", "source": "seed", "provider": "LBMA", "timestamp": "1985-10-22 12:00:00"}, {"spot": 6.13, "metal": "Silver", "source": "seed", "provider": "LBMA", "timestamp": "1985-10-22 12:00:00"}, {"spot": 326.9, "metal": "Gold", "source": "seed", "provider": "LBMA", "timestamp": "1985-10-23 12:00:00"}, {"spot": 6.205, "metal": "Silver", "source": "seed", "provider": "LBMA", "timestamp": "1985-10-23 12:00:00"}, {"spot": 325.95, "metal": "Gold", "source": "seed", "provider": "LBMA", "timestamp": "1985-10-24 12:00:00"}, {"spot": 6.172, "metal": "Silver", "source": "seed", "provider": "LBMA", "timestamp": "1985-10-24 12:00:00"}, {"spot": 325.65, "metal": "Gold", "source": "seed", "provider": "LBMA", "timestamp": "1985-10-25 12:00:00"}, {"spot": 6.162, "metal": "Silver", "source": "seed", "provider": "LBMA", "timestamp": "1985-10-25 12:00:00"}, {"spot": 326.5, "metal": "Gold", "source": "seed", "provider": "LBMA", "timestamp": "1985-10-28 12:00:00"}, {"spot": 6.155, "metal": "Silver", "source": "seed", "provider": "LBMA", "timestamp": "1985-10-28 12:00:00"}, {"spot": 326.55, "metal": "Gold", "source": "seed", "provider": "LBMA", "timestamp": "1985-10-29 12:00:00"}, {"spot": 6.175, "metal": "Silver", "source": "seed", "provider": "LBMA", "timestamp": "1985-10-29 12:00:00"}, {"spot": 326.8, "metal": "Gold", "source": "seed", "provider": "LBMA", "timestamp": "1985-10-30 12:00:00"}, {"spot": 6.135, "metal": "Silver", "source": "seed", "provider": "LBMA", "timestamp": "1985-10-30 12:00:00"}, {"spot": 325.75, "metal": "Gold", "source": "seed", "provider": "LBMA", "timestamp": "1985-10-31 12:00:00"}, {"spot": 6.145, "metal": "Silver", "source": "seed", "provider": "LBMA", "timestamp": "1985-10-31 12:00:00"}, {"spot": 324.65, "metal": "Gold", "source": "seed", "provider": "LBMA", "timestamp": "1985-11-01 12:00:00"}, {"spot": 6.068, "metal": "Silver", "source": "seed", "provider": "LBMA", "timestamp": "1985-11-01 12:00:00"}, {"spot": 325.6, "metal": "Gold", "source": "seed", "provider": "LBMA", "timestamp": "1985-11-04 12:00:00"}, {"spot": 6.079, "metal": "Silver", "source": "seed", "provider": "LBMA", "timestamp": "1985-11-04 12:00:00"}, {"spot": 324.55, "metal": "Gold", "source": "seed", "provider": "LBMA", "timestamp": "1985-11-05 12:00:00"}, {"spot": 6.071, "metal": "Silver", "source": "seed", "provider": "LBMA", "timestamp": "1985-11-05 12:00:00"}, {"spot": 324.75, "metal": "Gold", "source": "seed", "provider": "LBMA", "timestamp": "1985-11-06 12:00:00"}, {"spot": 6.075, "metal": "Silver", "source": "seed", "provider": "LBMA", "timestamp": "1985-11-06 12:00:00"}, {"spot": 323.6, "metal": "Gold", "source": "seed", "provider": "LBMA", "timestamp": "1985-11-07 12:00:00"}, {"spot": 6.06, "metal": "Silver", "source": "seed", "provider": "LBMA", "timestamp": "1985-11-07 12:00:00"}, {"spot": 322.1, "metal": "Gold", "source": "seed", "provider": "LBMA", "timestamp": "1985-11-08 12:00:00"}, {"spot": 6.04, "metal": "Silver", "source": "seed", "provider": "LBMA", "timestamp": "1985-11-08 12:00:00"}, {"spot": 323.25, "metal": "Gold", "source": "seed", "provider": "LBMA", "timestamp": "1985-11-11 12:00:00"}, {"spot": 6.078, "metal": "Silver", "source": "seed", "provider": "LBMA", "timestamp": "1985-11-11 12:00:00"}, {"spot": 322.7, "metal": "Gold", "source": "seed", "provider": "LBMA", "timestamp": "1985-11-12 12:00:00"}, {"spot": 6.083, "metal": "Silver", "source": "seed", "provider": "LBMA", "timestamp": "1985-11-12 12:00:00"}, {"spot": 324.5, "metal": "Gold", "source": "seed", "provider": "LBMA", "timestamp": "1985-11-13 12:00:00"}, {"spot": 6.125, "metal": "Silver", "source": "seed", "provider": "LBMA", "timestamp": "1985-11-13 12:00:00"}, {"spot": 325.0, "metal": "Gold", "source": "seed", "provider": "LBMA", "timestamp": "1985-11-14 12:00:00"}, {"spot": 6.15, "metal": "Silver", "source": "seed", "provider": "LBMA", "timestamp": "1985-11-14 12:00:00"}, {"spot": 324.55, "metal": "Gold", "source": "seed", "provider": "LBMA", "timestamp": "1985-11-15 12:00:00"}, {"spot": 6.115, "metal": "Silver", "source": "seed", "provider": "LBMA", "timestamp": "1985-11-15 12:00:00"}, {"spot": 323.75, "metal": "Gold", "source": "seed", "provider": "LBMA", "timestamp": "1985-11-18 12:00:00"}, {"spot": 6.09, "metal": "Silver", "source": "seed", "provider": "LBMA", "timestamp": "1985-11-18 12:00:00"}, {"spot": 324.1, "metal": "Gold", "source": "seed", "provider": "LBMA", "timestamp": "1985-11-19 12:00:00"}, {"spot": 6.091, "metal": "Silver", "source": "seed", "provider": "LBMA", "timestamp": "1985-11-19 12:00:00"}, {"spot": 325.05, "metal": "Gold", "source": "seed", "provider": "LBMA", "timestamp": "1985-11-20 12:00:00"}, {"spot": 6.174, "metal": "Silver", "source": "seed", "provider": "LBMA", "timestamp": "1985-11-20 12:00:00"}, {"spot": 325.75, "metal": "Gold", "source": "seed", "provider": "LBMA", "timestamp": "1985-11-21 12:00:00"}, {"spot": 6.17, "metal": "Silver", "source": "seed", "provider": "LBMA", "timestamp": "1985-11-21 12:00:00"}, {"spot": 326.0, "metal": "Gold", "source": "seed", "provider": "LBMA", "timestamp": "1985-11-22 12:00:00"}, {"spot": 6.153, "metal": "Silver", "source": "seed", "provider": "LBMA", "timestamp": "1985-11-22 12:00:00"}, {"spot": 330.5, "metal": "Gold", "source": "seed", "provider": "LBMA", "timestamp": "1985-11-25 12:00:00"}, {"spot": 6.25, "metal": "Silver", "source": "seed", "provider": "LBMA", "timestamp": "1985-11-25 12:00:00"}, {"spot": 331.5, "metal": "Gold", "source": "seed", "provider": "LBMA", "timestamp": "1985-11-26 12:00:00"}, {"spot": 6.246, "metal": "Silver", "source": "seed", "provider": "LBMA", "timestamp": "1985-11-26 12:00:00"}, {"spot": 330.45, "metal": "Gold", "source": "seed", "provider": "LBMA", "timestamp": "1985-11-27 12:00:00"}, {"spot": 6.213, "metal": "Silver", "source": "seed", "provider": "LBMA", "timestamp": "1985-11-27 12:00:00"}, {"spot": 326.75, "metal": "Gold", "source": "seed", "provider": "LBMA", "timestamp": "1985-11-28 12:00:00"}, {"spot": 6.135, "metal": "Silver", "source": "seed", "provider": "LBMA", "timestamp": "1985-11-28 12:00:00"}, {"spot": 327.4, "metal": "Gold", "source": "seed", "provider": "LBMA", "timestamp": "1985-11-29 12:00:00"}, {"spot": 6.15, "metal": "Silver", "source": "seed", "provider": "LBMA", "timestamp": "1985-11-29 12:00:00"}, {"spot": 323.95, "metal": "Gold", "source": "seed", "provider": "LBMA", "timestamp": "1985-12-02 12:00:00"}, {"spot": 6.102, "metal": "Silver", "source": "seed", "provider": "LBMA", "timestamp": "1985-12-02 12:00:00"}, {"spot": 322.5, "metal": "Gold", "source": "seed", "provider": "LBMA", "timestamp": "1985-12-03 12:00:00"}, {"spot": 6.075, "metal": "Silver", "source": "seed", "provider": "LBMA", "timestamp": "1985-12-03 12:00:00"}, {"spot": 324.5, "metal": "Gold", "source": "seed", "provider": "LBMA", "timestamp": "1985-12-04 12:00:00"}, {"spot": 6.08, "metal": "Silver", "source": "seed", "provider": "LBMA", "timestamp": "1985-12-04 12:00:00"}, {"spot": 322.5, "metal": "Gold", "source": "seed", "provider": "LBMA", "timestamp": "1985-12-05 12:00:00"}, {"spot": 6.058, "metal": "Silver", "source": "seed", "provider": "LBMA", "timestamp": "1985-12-05 12:00:00"}, {"spot": 322.5, "metal": "Gold", "source": "seed", "provider": "LBMA", "timestamp": "1985-12-06 12:00:00"}, {"spot": 6.056, "metal": "Silver", "source": "seed", "provider": "LBMA", "timestamp": "1985-12-06 12:00:00"}, {"spot": 320.15, "metal": "Gold", "source": "seed", "provider": "LBMA", "timestamp": "1985-12-09 12:00:00"}, {"spot": 5.985, "metal": "Silver", "source": "seed", "provider": "LBMA", "timestamp": "1985-12-09 12:00:00"}, {"spot": 316.1, "metal": "Gold", "source": "seed", "provider": "LBMA", "timestamp": "1985-12-10 12:00:00"}, {"spot": 5.81, "metal": "Silver", "source": "seed", "provider": "LBMA", "timestamp": "1985-12-10 12:00:00"}, {"spot": 316.8, "metal": "Gold", "source": "seed", "provider": "LBMA", "timestamp": "1985-12-11 12:00:00"}, {"spot": 5.795, "metal": "Silver", "source": "seed", "provider": "LBMA", "timestamp": "1985-12-11 12:00:00"}, {"spot": 316.05, "metal": "Gold", "source": "seed", "provider": "LBMA", "timestamp": "1985-12-12 12:00:00"}, {"spot": 5.775, "metal": "Silver", "source": "seed", "provider": "LBMA", "timestamp": "1985-12-12 12:00:00"}, {"spot": 317.9, "metal": "Gold", "source": "seed", "provider": "LBMA", "timestamp": "1985-12-13 12:00:00"}, {"spot": 5.874, "metal": "Silver", "source": "seed", "provider": "LBMA", "timestamp": "1985-12-13 12:00:00"}, {"spot": 318.25, "metal": "Gold", "source": "seed", "provider": "LBMA", "timestamp": "1985-12-16 12:00:00"}, {"spot": 5.843, "metal": "Silver", "source": "seed", "provider": "LBMA", "timestamp": "1985-12-16 12:00:00"}, {"spot": 321.9, "metal": "Gold", "source": "seed", "provider": "LBMA", "timestamp": "1985-12-17 12:00:00"}, {"spot": 5.903, "metal": "Silver", "source": "seed", "provider": "LBMA", "timestamp": "1985-12-17 12:00:00"}, {"spot": 321.1, "metal": "Gold", "source": "seed", "provider": "LBMA", "timestamp": "1985-12-18 12:00:00"}, {"spot": 5.76, "metal": "Silver", "source": "seed", "provider": "LBMA", "timestamp": "1985-12-18 12:00:00"}, {"spot": 323.4, "metal": "Gold", "source": "seed", "provider": "LBMA", "timestamp": "1985-12-19 12:00:00"}, {"spot": 5.82, "metal": "Silver", "source": "seed", "provider": "LBMA", "timestamp": "1985-12-19 12:00:00"}, {"spot": 323.55, "metal": "Gold", "source": "seed", "provider": "LBMA", "timestamp": "1985-12-20 12:00:00"}, {"spot": 5.828, "metal": "Silver", "source": "seed", "provider": "LBMA", "timestamp": "1985-12-20 12:00:00"}, {"spot": 325.75, "metal": "Gold", "source": "seed", "provider": "LBMA", "timestamp": "1985-12-23 12:00:00"}, {"spot": 5.858, "metal": "Silver", "source": "seed", "provider": "LBMA", "timestamp": "1985-12-23 12:00:00"}, {"spot": 324.85, "metal": "Gold", "source": "seed", "provider": "LBMA", "timestamp": "1985-12-24 12:00:00"}, {"spot": 5.78, "metal": "Silver", "source": "seed", "provider": "LBMA", "timestamp": "1985-12-24 12:00:00"}, {"spot": 324.8, "metal": "Gold", "source": "seed", "provider": "LBMA", "timestamp": "1985-12-27 12:00:00"}, {"spot": 5.778, "metal": "Silver", "source": "seed", "provider": "LBMA", "timestamp": "1985-12-27 12:00:00"}, {"spot": 326.15, "metal": "Gold", "source": "seed", "provider": "LBMA", "timestamp": "1985-12-30 12:00:00"}, {"spot": 5.867, "metal": "Silver", "source": "seed", "provider": "LBMA", "timestamp": "1985-12-30 12:00:00"}, {"spot": 327.0, "metal": "Gold", "source": "seed", "provider": "LBMA", "timestamp": "1985-12-31 12:00:00"}, {"spot": 5.8, "metal": "Silver", "source": "seed", "provider": "LBMA", "timestamp": "1985-12-31 12:00:00"}]