[
  {
    "spot": 5096.66,
    "metal": "Gold",
    "source": "hourly",
    "provider": "StakTrakr",
    "timestamp": "2026-03-09 16:00:00"
  },
  {
    "spot": 1661.46,
    "metal": "Palladium",
    "source": "hourly",
    "provider": "StakTrakr",
    "timestamp": "2026-03-09 16:00:00"
  },
  {
    "spot": 2160.66,
    "metal": "Platinum",
    "source": "hourly",
    "provider": "StakTrakr",
    "timestamp": "2026-03-09 16:00:00"
  },
  {
    "spot": 84.58,
    "metal": "Silver",
    "source": "hourly",
    "provider": "StakTrakr",
    "timestamp": "2026-03-09 16:00:00"
  }
]
