[
  {
    "spot": 5189.44,
    "metal": "Gold",
    "source": "seed",
    "provider": "StakTrakr",
    "timestamp": "2026-02-27 07:05:00"
  },
  {
    "spot": 90.27,
    "metal": "Silver",
    "source": "seed",
    "provider": "StakTrakr",
    "timestamp": "2026-02-27 07:05:00"
  },
  {
    "spot": 2408.16,
    "metal": "Platinum",
    "source": "seed",
    "provider": "StakTrakr",
    "timestamp": "2026-02-27 07:05:00"
  },
  {
    "spot": 1832.1,
    "metal": "Palladium",
    "source": "seed",
    "provider": "StakTrakr",
    "timestamp": "2026-02-27 07:05:00"
  }
]