[
  {
    "spot": 5302.97,
    "metal": "Gold",
    "source": "seed",
    "provider": "StakTrakr",
    "timestamp": "2026-03-02 18:30:01"
  },
  {
    "spot": 88.44,
    "metal": "Silver",
    "source": "seed",
    "provider": "StakTrakr",
    "timestamp": "2026-03-02 18:30:01"
  },
  {
    "spot": 2303.54,
    "metal": "Platinum",
    "source": "seed",
    "provider": "StakTrakr",
    "timestamp": "2026-03-02 18:30:01"
  },
  {
    "spot": 1745.74,
    "metal": "Palladium",
    "source": "seed",
    "provider": "StakTrakr",
    "timestamp": "2026-03-02 18:30:01"
  }
]