{
  "window_start": "2026-03-09T13:30:00Z",
  "generated_at": "2026-03-09T13:53:02.221Z",
  "coin_count": 23,
  "coins": {
    "age": {
      "window_start": "2026-03-09T13:30:00Z",
      "median_price": 5342.34,
      "lowest_price": 5210.77,
      "vendor_count": 6
    },
    "ape": {
      "window_start": "2026-03-09T13:30:00Z",
      "median_price": 2483.69,
      "lowest_price": 2345.62,
      "vendor_count": 5
    },
    "ase": {
      "window_start": "2026-03-09T13:30:00Z",
      "median_price": 94.95,
      "lowest_price": 92.39,
      "vendor_count": 4
    },
    "britannia-silver": {
      "window_start": "2026-03-09T13:30:00Z",
      "median_price": 97.64,
      "lowest_price": 90.98,
      "vendor_count": 4
    },
    "buffalo": {
      "window_start": "2026-03-09T13:30:00Z",
      "median_price": 5336.09,
      "lowest_price": 5249.64,
      "vendor_count": 3
    },
    "generic-silver-bar-10oz": {
      "window_start": "2026-03-09T13:30:00Z",
      "median_price": 936.66,
      "lowest_price": 882.18,
      "vendor_count": 5
    },
    "generic-silver-round": {
      "window_start": "2026-03-09T13:30:00Z",
      "median_price": 89.15,
      "lowest_price": 86.76,
      "vendor_count": 5
    },
    "goldback-arizona-g1": {
      "window_start": "2026-03-09T13:30:00Z",
      "median_price": 9.92,
      "lowest_price": 9.81,
      "vendor_count": 4
    },
    "goldback-dc-g1": {
      "window_start": "2026-03-09T13:30:00Z",
      "median_price": 8.6,
      "lowest_price": 8.6,
      "vendor_count": 1
    },
    "goldback-florida-g1": {
      "window_start": "2026-03-09T13:30:00Z",
      "median_price": 21.5,
      "lowest_price": 9.92,
      "vendor_count": 2
    },
    "goldback-nevada-g1": {
      "window_start": "2026-03-09T13:30:00Z",
      "median_price": 9.96,
      "lowest_price": 9.93,
      "vendor_count": 2
    },
    "goldback-new-hampshire-g1": {
      "window_start": "2026-03-09T13:30:00Z",
      "median_price": 9.92,
      "lowest_price": 9.81,
      "vendor_count": 3
    },
    "goldback-oklahoma-g1": {
      "window_start": "2026-03-09T13:30:00Z",
      "median_price": 9.92,
      "lowest_price": 9.81,
      "vendor_count": 3
    },
    "goldback-south-dakota-g1": {
      "window_start": "2026-03-09T13:30:00Z",
      "median_price": 9.96,
      "lowest_price": 9.94,
      "vendor_count": 3
    },
    "goldback-utah-g1": {
      "window_start": "2026-03-09T13:30:00Z",
      "median_price": 9.83,
      "lowest_price": 8.9,
      "vendor_count": 3
    },
    "goldback-wyoming-g1": {
      "window_start": "2026-03-09T13:30:00Z",
      "median_price": 9.93,
      "lowest_price": 9.8,
      "vendor_count": 3
    },
    "kangaroo-silver": {
      "window_start": "2026-03-09T13:30:00Z",
      "median_price": 91.48,
      "lowest_price": 89.19,
      "vendor_count": 6,
      "is_stale": true
    },
    "koala-silver": {
      "window_start": "2026-03-09T13:30:00Z",
      "median_price": 96.91,
      "lowest_price": 96.91,
      "vendor_count": 2
    },
    "kookaburra-silver": {
      "window_start": "2026-03-09T13:30:00Z",
      "median_price": 95.62,
      "lowest_price": 88.23,
      "vendor_count": 3
    },
    "krugerrand-gold": {
      "window_start": "2026-03-09T13:30:00Z",
      "median_price": 5192.73,
      "lowest_price": 5159.35,
      "vendor_count": 4
    },
    "krugerrand-silver": {
      "window_start": "2026-03-09T13:30:00Z",
      "median_price": 94.68,
      "lowest_price": 91.35,
      "vendor_count": 4
    },
    "maple-gold": {
      "window_start": "2026-03-09T13:30:00Z",
      "median_price": 5210.03,
      "lowest_price": 5167.51,
      "vendor_count": 5
    },
    "maple-silver": {
      "window_start": "2026-03-09T13:30:00Z",
      "median_price": 92.64,
      "lowest_price": 91.74,
      "vendor_count": 2
    }
  }
}
