{
  "window_start": "2026-02-24T14:30:00Z",
  "generated_at": "2026-02-24T14:38:01.741Z",
  "coin_count": 11,
  "coins": {
    "age": {
      "window_start": "2026-02-24T14:30:00Z",
      "median_price": 5301.55,
      "lowest_price": 5191.79,
      "vendor_count": 5
    },
    "ape": {
      "window_start": "2026-02-24T14:30:00Z",
      "median_price": 2436.79,
      "lowest_price": 2396.08,
      "vendor_count": 6
    },
    "ase": {
      "window_start": "2026-02-24T14:30:00Z",
      "median_price": 103.15,
      "lowest_price": 97.59,
      "vendor_count": 7
    },
    "britannia-silver": {
      "window_start": "2026-02-24T14:30:00Z",
      "median_price": 97.81,
      "lowest_price": 95.18,
      "vendor_count": 6
    },
    "buffalo": {
      "window_start": "2026-02-24T14:30:00Z",
      "median_price": 5418.61,
      "lowest_price": 5337,
      "vendor_count": 6
    },
    "generic-silver-bar-10oz": {
      "window_start": "2026-02-24T14:30:00Z",
      "median_price": 976,
      "lowest_price": 904.9,
      "vendor_count": 4
    },
    "generic-silver-round": {
      "window_start": "2026-02-24T14:30:00Z",
      "median_price": 92.75,
      "lowest_price": 89.19,
      "vendor_count": 6
    },
    "krugerrand-gold": {
      "window_start": "2026-02-24T14:30:00Z",
      "median_price": 5195,
      "lowest_price": 5138.59,
      "vendor_count": 6
    },
    "krugerrand-silver": {
      "window_start": "2026-02-24T14:30:00Z",
      "median_price": 98.19,
      "lowest_price": 93.55,
      "vendor_count": 6
    },
    "maple-gold": {
      "window_start": "2026-02-24T14:30:00Z",
      "median_price": 5247.88,
      "lowest_price": 5206.4,
      "vendor_count": 6
    },
    "maple-silver": {
      "window_start": "2026-02-24T14:30:00Z",
      "median_price": 98.09,
      "lowest_price": 91.59,
      "vendor_count": 6
    }
  }
}
