{
  "window_start": "2026-02-24T21:15:00Z",
  "generated_at": "2026-02-24T21:23:08.862Z",
  "coin_count": 11,
  "coins": {
    "age": {
      "window_start": "2026-02-24T21:15:00Z",
      "median_price": 5164,
      "lowest_price": 5164,
      "vendor_count": 2
    },
    "ape": {
      "window_start": "2026-02-24T21:15:00Z",
      "median_price": 5160.7,
      "lowest_price": 2474.59,
      "vendor_count": 3
    },
    "ase": {
      "window_start": "2026-02-24T21:15:00Z",
      "median_price": 103.69,
      "lowest_price": 103.69,
      "vendor_count": 3
    },
    "britannia-silver": {
      "window_start": "2026-02-24T21:15:00Z",
      "median_price": 98.12,
      "lowest_price": 95.88,
      "vendor_count": 3
    },
    "buffalo": {
      "window_start": "2026-02-24T21:15:00Z",
      "median_price": 5463.88,
      "lowest_price": 5163.3,
      "vendor_count": 4
    },
    "generic-silver-bar-10oz": {
      "window_start": "2026-02-24T21:15:00Z",
      "median_price": 922.64,
      "lowest_price": 914.9,
      "vendor_count": 5
    },
    "generic-silver-round": {
      "window_start": "2026-02-24T21:15:00Z",
      "median_price": 91.92,
      "lowest_price": 87.7,
      "vendor_count": 5
    },
    "krugerrand-gold": {
      "window_start": "2026-02-24T21:15:00Z",
      "median_price": 5229.64,
      "lowest_price": 5169.6,
      "vendor_count": 4
    },
    "krugerrand-silver": {
      "window_start": "2026-02-24T21:15:00Z",
      "median_price": 94.84,
      "lowest_price": 94.43,
      "vendor_count": 5
    },
    "maple-gold": {
      "window_start": "2026-02-24T21:15:00Z",
      "median_price": 5268.96,
      "lowest_price": 5160.7,
      "vendor_count": 4
    },
    "maple-silver": {
      "window_start": "2026-02-24T21:15:00Z",
      "median_price": 99.45,
      "lowest_price": 87.74,
      "vendor_count": 3
    }
  }
}
